qkmd/__init__.py
qkmd/qkmd.py
qkmd-1.0.3.dist-info/LICENSE
qkmd-1.0.3.dist-info/METADATA
qkmd-1.0.3.dist-info/WHEEL
qkmd-1.0.3.dist-info/entry_points.txt
qkmd-1.0.3.dist-info/top_level.txt
qkmd-1.0.3.dist-info/RECORD
