Metadata-Version: 2.1
Name: qkmd
Version: 1.0.3
Summary: Quick markdown what you need, just via a link.
Home-page: https://github.com/Alopex4/qkmd
Author: alopex cheung
Author-email: alopex4@163.com
License: MIT
Platform: UNKNOWN
Classifier: Environment :: Console
Classifier: Programming Language :: Python :: 3.4
Classifier: Programming Language :: Python :: 3.5
Classifier: Programming Language :: Python :: 3.6
Classifier: License :: OSI Approved :: MIT License
Classifier: Operating System :: POSIX :: Linux
Classifier: Topic :: Documentation
Requires-Dist: pyquery
Requires-Dist: pygments
Requires-Dist: requests
